docs/source/conf.py
examples/dde_demo.py
examples/ilt_demo.py
examples/simple_demo.py
examples/simple_demo_double_precision.py
experiments/datasets.py
experiments/exp_all_baselines.py
experiments/utils.py
experiments/baseline_models/__init__.py
experiments/baseline_models/data_utils.py
experiments/baseline_models/flow.py
experiments/baseline_models/gru.py
experiments/baseline_models/lstm.py
experiments/baseline_models/neural_laplace.py
experiments/baseline_models/ode.py
experiments/baseline_models/ode_models.py
experiments/baseline_models/original_latent_ode.py
experiments/baseline_models/original_ode_models.py
experiments/baseline_models/latent_ode_lib/__init__.py
experiments/baseline_models/latent_ode_lib/base_models.py
experiments/baseline_models/latent_ode_lib/create_latent_ode_model.py
experiments/baseline_models/latent_ode_lib/diffeq_solver.py
experiments/baseline_models/latent_ode_lib/encoder_decoder.py
experiments/baseline_models/latent_ode_lib/latent_ode.py
experiments/baseline_models/latent_ode_lib/likelihood_eval.py
experiments/baseline_models/latent_ode_lib/ode_func.py
experiments/baseline_models/latent_ode_lib/ode_rnn.py
experiments/baseline_models/latent_ode_lib/parse_datasets.py
experiments/baseline_models/latent_ode_lib/plotting.py
experiments/baseline_models/latent_ode_lib/rnn_baselines.py
experiments/baseline_models/latent_ode_lib/utils.py
torchlaplace/__init__.py
torchlaplace/_iltcme.py
torchlaplace/core.py
torchlaplace/data_utils.py
torchlaplace/inverse_laplace.py
torchlaplace/transformations.py
torchlaplace/version.py
torchlaplace-0.0.4.dist-info/LICENSE
torchlaplace-0.0.4.dist-info/METADATA
torchlaplace-0.0.4.dist-info/WHEEL
torchlaplace-0.0.4.dist-info/top_level.txt
torchlaplace-0.0.4.dist-info/RECORD
