Metadata-Version: 2.1
Name: torchlaplace
Version: 0.0.4
Summary: Differentiable Laplace Reconstructions in PyTorch
Home-page: https://github.com/samholt/NeuralLaplace
Author: Sam Holt
Author-email: samuel.holt.direct@gmail.com
License: MIT
Platform: any
Classifier: Programming Language :: Python :: 3
Classifier: Topic :: Scientific/Engineering :: Artificial Intelligence
Classifier: Intended Audience :: Science/Research
Classifier: License :: OSI Approved :: MIT License
Classifier: Operating System :: OS Independent
License-File: LICENSE
Requires-Dist: torch (>=1.3.0)
Requires-Dist: scipy (>=1.4.0)
Requires-Dist: importlib-metadata ; python_version < "3.8"
Provides-Extra: experiments
Requires-Dist: ddeint ; extra == 'experiments'
Requires-Dist: keyboard ; extra == 'experiments'
Requires-Dist: matplotlib ; extra == 'experiments'
Requires-Dist: pandas ; extra == 'experiments'
Requires-Dist: sklearn ; extra == 'experiments'
Requires-Dist: stribor (==0.1.0) ; extra == 'experiments'
Requires-Dist: torchdiffeq (>=0.2.1) ; extra == 'experiments'
Requires-Dist: torchvision ; extra == 'experiments'
Requires-Dist: tqdm ; extra == 'experiments'
Requires-Dist: Sphinx ; extra == 'experiments'
Requires-Dist: sphinx-rtd-theme ; extra == 'experiments'
Requires-Dist: sphinx-panels ; extra == 'experiments'
Requires-Dist: nbsphinx ; extra == 'experiments'
Provides-Extra: testing
Requires-Dist: setuptools ; extra == 'testing'
Requires-Dist: pytest ; extra == 'testing'
Requires-Dist: pytest-cov ; extra == 'testing'
Requires-Dist: pytest-benchmark ; extra == 'testing'
Requires-Dist: tabulate ; extra == 'testing'
Requires-Dist: bandit ; extra == 'testing'
Requires-Dist: black ; extra == 'testing'
Requires-Dist: flake8 ; extra == 'testing'
Requires-Dist: pre-commit ; extra == 'testing'
Requires-Dist: xlrd ; extra == 'testing'
